odoo/addons/pos_early_receipt_printing/README.rst
odoo/addons/pos_early_receipt_printing/__init__.py
odoo/addons/pos_early_receipt_printing/__manifest__.py
odoo/addons/pos_early_receipt_printing/i18n/ca_ES.po
odoo/addons/pos_early_receipt_printing/i18n/es.po
odoo/addons/pos_early_receipt_printing/i18n/it.po
odoo/addons/pos_early_receipt_printing/i18n/pos_early_receipt_printing.pot
odoo/addons/pos_early_receipt_printing/models/__init__.py
odoo/addons/pos_early_receipt_printing/models/res_config_settings.py
odoo/addons/pos_early_receipt_printing/readme/CONFIGURE.md
odoo/addons/pos_early_receipt_printing/readme/CONTRIBUTORS.md
odoo/addons/pos_early_receipt_printing/readme/DESCRIPTION.md
odoo/addons/pos_early_receipt_printing/readme/USAGE.md
odoo/addons/pos_early_receipt_printing/static/description/icon.png
odoo/addons/pos_early_receipt_printing/static/description/index.html
odoo/addons/pos_early_receipt_printing/views/pos_config_views.xml
odoo_addon_pos_early_receipt_printing-17.0.1.0.0.4.dist-info/METADATA
odoo_addon_pos_early_receipt_printing-17.0.1.0.0.4.dist-info/WHEEL
odoo_addon_pos_early_receipt_printing-17.0.1.0.0.4.dist-info/top_level.txt
odoo_addon_pos_early_receipt_printing-17.0.1.0.0.4.dist-info/RECORD
